Metadata-Version: 1.0
Name: youtea
Version: 0.1.15
Summary: Display statistics from youtube video
Home-page: UNKNOWN
Author: UNKNOWN
Author-email: leykoderto@gmail.com
License: Copyright (c) 2021 SladkayaDoza
Platform: UNKNOWN
